pet/__init__.py
pet/cli.py
pet/commands/__init__.py
pet/commands/init_command.py
pet/commands/list_workspace_command.py
pet/commands/login_command.py
pet/commands/pack_command.py
pet/commands/pull_command.py
pet/commands/push_command.py
pet/commands/run_command.py
pet/commands/validate_command.py
python_extension_toolkit-1.0.0.dist-info/licenses/LICENSE
python_extension_toolkit-1.0.0.dist-info/METADATA
python_extension_toolkit-1.0.0.dist-info/WHEEL
python_extension_toolkit-1.0.0.dist-info/entry_points.txt
python_extension_toolkit-1.0.0.dist-info/top_level.txt
python_extension_toolkit-1.0.0.dist-info/RECORD
