Metadata-Version: 2.4
Name: python-extension-toolkit
Version: 1.0.0
Summary: A Python CLI tool for extension development (Python equivalent of Zoho Extension Toolkit)
Author-email: Python Extension Toolkit Team <pet@example.com>
License: MIT
Project-URL: Homepage, https://github.com/Aqary-Org/python-extension-toolkit
Project-URL: Documentation, https://github.com/Aqary-Org/python-extension-toolkit#readme
Project-URL: Repository, https://github.com/Aqary-Org/python-extension-toolkit.git
Project-URL: Bug Tracker, https://github.com/Aqary-Org/python-extension-toolkit/issues
Keywords: cli,extension,development,toolkit,pet,zoho
Classifier: Development Status :: 5 - Production/Stable
Classifier: Intended Audience :: Developers
Classifier: License :: OSI Approved :: MIT License
Classifier: Programming Language :: Python :: 3
Classifier: Programming Language :: Python :: 3.8
Classifier: Programming Language :: Python :: 3.9
Classifier: Programming Language :: Python :: 3.10
Classifier: Programming Language :: Python :: 3.11
Classifier: Programming Language :: Python :: 3.12
Classifier: Topic :: Software Development :: Libraries :: Python Modules
Classifier: Topic :: Software Development :: Build Tools
Requires-Python: >=3.8
License-File: LICENSE
Requires-Dist: click>=8.0.0
Requires-Dist: flask>=2.0.0
Requires-Dist: flask-cors>=4.0.0
Requires-Dist: requests>=2.25.0
Provides-Extra: dev
Requires-Dist: pytest>=6.0; extra == "dev"
Requires-Dist: black; extra == "dev"
Requires-Dist: flake8; extra == "dev"
Requires-Dist: mypy; extra == "dev"
Dynamic: license-file
